<?xml version="1.0"?>
<xml><data><code>1</code><pasien_awal>1</pasien_awal><pasien_masuk>4</pasien_masuk><pasien_keluar_hidup>3</pasien_keluar_hidup><pkm_k24>1</pkm_k24><pkm_l24>1</pkm_l24><lama_dirawat>10</lama_dirawat><super_vip>4</super_vip><vip>6</vip><kelas_1>15</kelas_1><kelas_2>34</kelas_2><kelas_3>108</kelas_3><kelas_khusus>10</kelas_khusus><pasien_jatuh>1</pasien_jatuh><pasien_jatuh>0</pasien_jatuh><jumlah_tt>20</jumlah_tt><pengembalian_rm>6</pengembalian_rm><j_hari>31</j_hari><umum>1</umum><bpjs>2</bpjs><jamkesda>1</jamkesda><lain>1</lain><smt>3</smt><tahun>2015</tahun></data></xml>
